resicli/__init__.py
resicli/cli.py
resicli/config.py
resicli/image_resizer.py
resicli/utils.py
resicli-1.0.0.dist-info/licenses/LICENSE
resicli-1.0.0.dist-info/METADATA
resicli-1.0.0.dist-info/WHEEL
resicli-1.0.0.dist-info/entry_points.txt
resicli-1.0.0.dist-info/top_level.txt
resicli-1.0.0.dist-info/RECORD
