Metadata-Version: 2.4
Name: resicli
Version: 1.0.0
Summary: A CLI tool for bulk image resizing
Home-page: https://github.com/gaikwadyash905/ResiCLI
Author: Yash Gaikwad
Author-email: Yash Gaikwad <gaikwadyash905@gmail.com>
Project-URL: Homepage, https://github.com/gaikwadyash905/ResiCLI
Keywords: image,resize,bulk,cli,pillow
Classifier: Development Status :: 4 - Beta
Classifier: Intended Audience :: Developers
Classifier: Programming Language :: Python :: 3
Classifier: Programming Language :: Python :: 3.7
Classifier: Programming Language :: Python :: 3.8
Classifier: Programming Language :: Python :: 3.9
Classifier: Programming Language :: Python :: 3.10
Classifier: License :: OSI Approved :: Apache Software License
Classifier: Operating System :: OS Independent
Classifier: Topic :: Multimedia :: Graphics
Classifier: Topic :: Utilities
Requires-Python: >=3.7
License-File: LICENSE
Requires-Dist: Pillow>=9.0.0
Requires-Dist: click>=8.0.0
Requires-Dist: tqdm>=4.65.0
Dynamic: author
Dynamic: home-page
Dynamic: license-file
Dynamic: requires-python
